README.md
pyproject.toml
setup.py
tritonserver/__init__.py
tritonserver.egg-info/PKG-INFO
tritonserver.egg-info/SOURCES.txt
tritonserver.egg-info/dependency_links.txt
tritonserver.egg-info/top_level.txt