Metadata-Version: 2.1
Name: tritonserver
Version: 0.0.1.dev0
Summary: A package to warn users about incorrect installation of Triton Server.
Author-email: Iman Tabrizian <itabrizian@nvidia.com>
License: BSD-3-Clause
Keywords: nvidia
Classifier: Programming Language :: Python :: 3
Requires-Python: >=3.8
